starlette_admin_litestar_plugin/__init__.py
starlette_admin_litestar_plugin/py.typed
starlette_admin_litestar_plugin/ext/__init__.py
starlette_admin_litestar_plugin/ext/advanced_alchemy.py
starlette_admin_litestar_plugin-0.3.2.dist-info/METADATA
starlette_admin_litestar_plugin-0.3.2.dist-info/WHEEL
starlette_admin_litestar_plugin-0.3.2.dist-info/licenses/LICENSE
starlette_admin_litestar_plugin-0.3.2.dist-info/RECORD
