Metadata-Version: 2.4
Name: starlette-admin-litestar-plugin
Version: 0.3.2
Summary: Starlette Admin plugin for LiteStar
Project-URL: Changelog, https://github.com/noamsto/starlette-admin-litestar-plugin/blob/main/CHANGELOG.md
Project-URL: Issues, https://github.com/noamsto/starlette-admin-litestar-plugin/issues
Project-URL: Repository, https://github.com/noamsto/starlette-admin-litestar-plugin
Author-email: Noam Stolero <noamstolero@gmail.com>
License-Expression: MIT
License-File: LICENSE
Keywords: admin,advanced-alchemy,dashboard,datatables,litestar,sqlalchemy,starlette
Requires-Python: >=3.10
Requires-Dist: litestar>=2.14.0
Requires-Dist: pydantic>=2.10.6
Requires-Dist: starlette-admin>=0.15.1
Requires-Dist: starlette>=0.45.3
